LICENSE
README.md
setup.py
litelab/__init__.py
litelab/lab.py
litelab/lite.py
litelab/requirements.txt
litelab.egg-info/PKG-INFO
litelab.egg-info/SOURCES.txt
litelab.egg-info/dependency_links.txt
litelab.egg-info/entry_points.txt
litelab.egg-info/requires.txt
litelab.egg-info/top_level.txt