Metadata-Version: 2.1
Name: litelab
Version: 0.0.2
Summary: Create lightweight configs for instantiating ML experiments
Home-page: https://github.com/1lint/litelab
Author: 1lint
Author-email: 105617163+1lint@users.noreply.github.com
License-File: LICENSE
